typegun/__init__.py
typegun-1.0.1.dist-info/METADATA
typegun-1.0.1.dist-info/WHEEL
typegun-1.0.1.dist-info/entry_points.txt
typegun-1.0.1.dist-info/licenses/LICENSE.txt
typegun-1.0.1.dist-info/RECORD
