Metadata-Version: 2.4
Name: typegun
Version: 1.0.1
Summary: Run a bunch of python typecheckers on a project, to see if there are any problems.
Author-email: wyattscarpenter <wyattscarpenter@gmail.com>
License-Expression: CC0-1.0
License-File: LICENSE.txt
Requires-Python: >=3.9
Requires-Dist: mypy
Requires-Dist: pyright
Requires-Dist: pytype
Requires-Dist: ruff
